Metadata-Version: 2.1
Name: odoo14-addon-product_harmonized_system_stock
Version: 14.0.1.0.1.dev7
Summary: Adds a menu entry for H.S. codes
Home-page: https://github.com/OCA/intrastat-extrastat
Author: Akretion, Odoo Community Association (OCA)
Author-email: support@odoo-community.org
License: AGPL-3
Classifier: Programming Language :: Python
Classifier: Framework :: Odoo
Classifier: Framework :: Odoo :: 14.0
Classifier: License :: OSI Approved :: GNU Affero General Public License v3
Requires-Python: >=3.6
Requires-Dist: odoo14-addon-product-harmonized-system
Requires-Dist: odoo<14.1dev,>=14.0a
